MANIFEST.in
requirements.txt
setup.py
theo.py
theo/__init__.py
theo/version.py
theo.egg-info/PKG-INFO
theo.egg-info/SOURCES.txt
theo.egg-info/dependency_links.txt
theo.egg-info/entry_points.txt
theo.egg-info/requires.txt
theo.egg-info/top_level.txt
theo/exploit/__init__.py
theo/exploit/exploit.py
theo/exploit/tx.py
theo/file/__init__.py
theo/interfaces/__init__.py
theo/interfaces/cli.py
theo/scanner/__init__.py