Metadata-Version: 2.1
Name: theo
Version: 0.8.2
Summary: UNKNOWN
Home-page: https://github.com/cleanunicorn/theo
Author: Daniel Luca
Author-email: daniel.luca@consensys.net
License: MIT
Platform: UNKNOWN
